<?xml version="1.0" encoding="utf-8"?>
<abapGit version="v1.0.0" serializer="LCL_OBJECT_VIEW" serializer_version="v1.0.0">
 <asx:abap xmlns:asx="http://www.sap.com/abapxml" version="1.0">
  <asx:values>
   <DD25V>
    <VIEWNAME>ZABSF_PP_V_SF002</VIEWNAME>
    <AS4LOCAL>A</AS4LOCAL>
    <AGGTYPE>V</AGGTYPE>
    <ROOTTAB>ZABSF_PP002</ROOTTAB>
    <VIEWCLASS>C</VIEWCLASS>
    <CUSTOMAUTH>C</CUSTOMAUTH>
    <GLOBALFLAG>X</GLOBALFLAG>
   </DD25V>
   <DD26V_TABLE>
    <DD26V>
     <VIEWNAME>ZABSF_PP_V_SF002</VIEWNAME>
     <TABNAME>ZABSF_PP002</TABNAME>
     <TABPOS>0001</TABPOS>
     <FORTABNAME>ZABSF_PP002</FORTABNAME>
    </DD26V>
   </DD26V_TABLE>
   <DD27P_TABLE>
    <DD27P>
     <VIEWFIELD>MANDT</VIEWFIELD>
     <TABNAME>ZABSF_PP002</TABNAME>
     <FIELDNAME>MANDT</FIELDNAME>
     <KEYFLAG>X</KEYFLAG>
     <CHECKTABLE>T000</CHECKTABLE>
     <SHLPORIGIN>P</SHLPORIGIN>
    </DD27P>
    <DD27P>
     <VIEWFIELD>AREAID</VIEWFIELD>
     <TABNAME>ZABSF_PP002</TABNAME>
     <FIELDNAME>AREAID</FIELDNAME>
     <KEYFLAG>X</KEYFLAG>
     <CHECKTABLE>ZABSF_PP000</CHECKTABLE>
     <SHLPORIGIN>P</SHLPORIGIN>
    </DD27P>
    <DD27P>
     <VIEWFIELD>WERKS</VIEWFIELD>
     <TABNAME>ZABSF_PP002</TABNAME>
     <FIELDNAME>WERKS</FIELDNAME>
     <KEYFLAG>X</KEYFLAG>
     <CHECKTABLE>T001W</CHECKTABLE>
     <SHLPORIGIN>P</SHLPORIGIN>
     <SHLPNAME>H_T001W_C</SHLPNAME>
     <SHLPFIELD>WERKS</SHLPFIELD>
     <LOGFLAG>X</LOGFLAG>
    </DD27P>
    <DD27P>
     <VIEWFIELD>SHIFTID</VIEWFIELD>
     <TABNAME>ZABSF_PP002</TABNAME>
     <FIELDNAME>SHIFTID</FIELDNAME>
     <KEYFLAG>X</KEYFLAG>
     <CHECKTABLE>ZABSF_PP001</CHECKTABLE>
     <SHLPORIGIN>P</SHLPORIGIN>
    </DD27P>
    <DD27P>
     <VIEWFIELD>HNAME</VIEWFIELD>
     <TABNAME>ZABSF_PP002</TABNAME>
     <FIELDNAME>HNAME</FIELDNAME>
     <KEYFLAG>X</KEYFLAG>
    </DD27P>
    <DD27P>
     <VIEWFIELD>ENDDA</VIEWFIELD>
     <TABNAME>ZABSF_PP002</TABNAME>
     <FIELDNAME>ENDDA</FIELDNAME>
     <KEYFLAG>X</KEYFLAG>
     <SHLPORIGIN>T</SHLPORIGIN>
    </DD27P>
    <DD27P>
     <VIEWFIELD>BEGDA</VIEWFIELD>
     <TABNAME>ZABSF_PP002</TABNAME>
     <FIELDNAME>BEGDA</FIELDNAME>
     <SHLPORIGIN>T</SHLPORIGIN>
    </DD27P>
    <DD27P>
     <VIEWFIELD>REG_QUANT</VIEWFIELD>
     <TABNAME>ZABSF_PP002</TABNAME>
     <FIELDNAME>REG_QUANT</FIELDNAME>
     <SHLPORIGIN>F</SHLPORIGIN>
     <VALEXI>X</VALEXI>
    </DD27P>
   </DD27P_TABLE>
   <I18N_LANGS>
    <LANGU>P</LANGU>
   </I18N_LANGS>
   <DD25_TEXTS>
    <item>
     <DDLANGUAGE>P</DDLANGUAGE>
     <DDTEXT>Shopfloor - Hierarquias por Área</DDTEXT>
    </item>
   </DD25_TEXTS>
  </asx:values>
 </asx:abap>
</abapGit>
